README
setup.cfg
setup.py
cotendo/__init__.py
cotendo/cotendohelper.py
cotendo/records.py
cotendo.egg-info/PKG-INFO
cotendo.egg-info/SOURCES.txt
cotendo.egg-info/dependency_links.txt
cotendo.egg-info/entry_points.txt
cotendo.egg-info/not-zip-safe
cotendo.egg-info/requires.txt
cotendo.egg-info/top_level.txt