Metadata-Version: 1.0
Name: cotendo
Version: 0.8dev
Summary: Cotendo API
Home-page: https://github.com/seryl/Python-Cotendo
Author: Josh Toft
Author-email: joshtoft@gmail.com
License: MIT
Keywords: Cotendo Python API
Platform: UNKNOWN
